{
  "last_node_id": 3,
  "last_link_id": 2,
  "nodes": [
    {
      "id": 1,
      "type": "Image Comparer (rgthree)",
      "pos": {
        "0": 975,
        "1": 60
      },
      "size": [
        658.5798047999997,
        682.6610323636363
      ],
      "flags": {},
      "order": 2,
      "mode": 0,
      "inputs": [
        {
          "name": "image_a",
          "type": "IMAGE",
          "link": 1,
          "dir": 3
        },
        {
          "name": "image_b",
          "type": "IMAGE",
          "link": 2,
          "dir": 3
        }
      ],
      "outputs": [],
      "properties": {
        "comparer_mode": "Slide"
      },
      "widgets_values": [
        [
          {
            "name": "A",
            "selected": true,
            "url": "/api/view?filename=rgthree.compare._temp_uzevq_00003_.png&type=temp&subfolder=&rand=0.5544305457178569"
          },
          {
            "name": "B",
            "selected": true,
            "url": "/api/view?filename=rgthree.compare._temp_uzevq_00004_.png&type=temp&subfolder=&rand=0.32837633602930116"
          }
        ]
      ]
    },
    {
      "id": 2,
      "type": "LoadImage",
      "pos": {
        "0": 648,
        "1": 57
      },
      "size": [
        315,
        314
      ],
      "flags": {},
      "order": 0,
      "mode": 0,
      "inputs": [],
      "outputs": [
        {
          "name": "IMAGE",
          "type": "IMAGE",
          "links": [
            1
          ],
          "slot_index": 0
        },
        {
          "name": "MASK",
          "type": "MASK",
          "links": null
        }
      ],
      "properties": {
        "Node name for S&R": "LoadImage"
      },
      "widgets_values": [
        "ComfyUI_00073_.png",
        "image"
      ]
    },
    {
      "id": 3,
      "type": "LoadImage",
      "pos": {
        "0": 651,
        "1": 434
      },
      "size": [
        315,
        314.00000381469727
      ],
      "flags": {},
      "order": 1,
      "mode": 0,
      "inputs": [],
      "outputs": [
        {
          "name": "IMAGE",
          "type": "IMAGE",
          "links": [
            2
          ],
          "slot_index": 0
        },
        {
          "name": "MASK",
          "type": "MASK",
          "links": null
        }
      ],
      "properties": {
        "Node name for S&R": "LoadImage"
      },
      "widgets_values": [
        "ComfyUI_00075_.png",
        "image"
      ]
    }
  ],
  "links": [
    [
      1,
      2,
      0,
      1,
      0,
      "IMAGE"
    ],
    [
      2,
      3,
      0,
      1,
      1,
      "IMAGE"
    ]
  ],
  "groups": [],
  "config": {},
  "extra": {
    "ds": {
      "scale": 1.3310000000000004,
      "offset": [
        -491.7851410885047,
        -76.4872292832457
      ]
    }
  },
  "version": 0.4
}